authpy/__init__.py
authpy/auth.py
authpy-2.1.1.dist-info/LICENSE
authpy-2.1.1.dist-info/METADATA
authpy-2.1.1.dist-info/WHEEL
authpy-2.1.1.dist-info/top_level.txt
authpy-2.1.1.dist-info/RECORD
